llama_verifications/__init__.py
llama_verifications/benchmarks/benchmarks/__init__.py
llama_verifications/benchmarks/benchmarks/registry.py
llama_verifications/benchmarks/benchmarks/ai2d/__init__.py
llama_verifications/benchmarks/benchmarks/ai2d/create_dataset.py
llama_verifications/benchmarks/benchmarks/ai2d/grader.py
llama_verifications/benchmarks/benchmarks/bfcl/__init__.py
llama_verifications/benchmarks/benchmarks/bfcl/create_dataset.py
llama_verifications/benchmarks/benchmarks/bfcl/grader.py
llama_verifications/benchmarks/benchmarks/bfcl/preprocessor.py
llama_verifications/benchmarks/benchmarks/bfcl_api/__init__.py
llama_verifications/benchmarks/benchmarks/common/__init__.py
llama_verifications/benchmarks/benchmarks/common/preprocessors.py
llama_verifications/benchmarks/benchmarks/common/graders/__init__.py
llama_verifications/benchmarks/benchmarks/common/graders/chrf.py
llama_verifications/benchmarks/benchmarks/common/graders/regex_parser_multiple_choice_grader.py
llama_verifications/benchmarks/benchmarks/docvqa/__init__.py
llama_verifications/benchmarks/benchmarks/docvqa/create_dataset.py
llama_verifications/benchmarks/benchmarks/docvqa/grader.py
llama_verifications/benchmarks/benchmarks/docvqa/preprocessor.py
llama_verifications/benchmarks/benchmarks/gpqa/__init__.py
llama_verifications/benchmarks/benchmarks/gpqa/create_dataset.py
llama_verifications/benchmarks/benchmarks/ifeval/__init__.py
llama_verifications/benchmarks/benchmarks/ifeval/create_dataset.py
llama_verifications/benchmarks/benchmarks/ifeval/grader.py
llama_verifications/benchmarks/benchmarks/ifeval/preprocessor.py
llama_verifications/benchmarks/benchmarks/ifeval/utils/ifeval_utils.py
llama_verifications/benchmarks/benchmarks/math500/__init__.py
llama_verifications/benchmarks/benchmarks/math500/create_dataset.py
llama_verifications/benchmarks/benchmarks/math500/grader.py
llama_verifications/benchmarks/benchmarks/mmlu_cot/__init__.py
llama_verifications-0.1.1.dist-info/licenses/LICENSE
llama_verifications-0.1.1.dist-info/METADATA
llama_verifications-0.1.1.dist-info/WHEEL
llama_verifications-0.1.1.dist-info/entry_points.txt
llama_verifications-0.1.1.dist-info/top_level.txt
llama_verifications-0.1.1.dist-info/RECORD
