Metadata-Version: 2.4
Name: llama-verifications
Version: 0.1.1
Summary: Llama Verifications
Author-email: Meta Llama <llama-oss@meta.com>
License: MIT
Classifier: License :: OSI Approved :: MIT License
Classifier: Programming Language :: Python :: 3
Classifier: Operating System :: OS Independent
Classifier: Intended Audience :: Developers
Classifier: Intended Audience :: Information Technology
Classifier: Intended Audience :: Science/Research
Classifier: Topic :: Scientific/Engineering :: Artificial Intelligence
Classifier: Topic :: Scientific/Engineering :: Information Analysis
Requires-Python: >=3.12
License-File: LICENSE
Requires-Dist: h11>=0.16.0
Requires-Dist: pydantic>=2
Requires-Dist: rich
Requires-Dist: setuptools
Requires-Dist: jsonlines
Requires-Dist: tqdm
Requires-Dist: loguru
Requires-Dist: datasets
Requires-Dist: click
Requires-Dist: openai
Requires-Dist: httpcore>=0.15.0
Requires-Dist: langdetect
Requires-Dist: emoji
Requires-Dist: nltk
Requires-Dist: pythainlp
Requires-Dist: pillow
Requires-Dist: sacrebleu
Requires-Dist: setuptools
Requires-Dist: tree-sitter
Requires-Dist: tree-sitter-java
Requires-Dist: tree-sitter-javascript
Requires-Dist: dotenv
Requires-Dist: pytest-json-report>=1.5.0
Requires-Dist: bfcl_eval
Provides-Extra: dev
Requires-Dist: pytest; extra == "dev"
Requires-Dist: pytest-asyncio; extra == "dev"
Requires-Dist: nbval; extra == "dev"
Requires-Dist: black; extra == "dev"
Requires-Dist: ruff; extra == "dev"
Requires-Dist: types-requests; extra == "dev"
Requires-Dist: types-setuptools; extra == "dev"
Requires-Dist: pre-commit; extra == "dev"
Requires-Dist: pip-tools; extra == "dev"
Dynamic: license-file
